{
  "posts": [
    {
      "id": "1",
      "title": "Darpan Coordinator",
      "sub":"",
      "name": "Ajish S",
      "ph": "9447789825"
    },
    {
      "id": "2",
      "title": "Student Coordinator",
      "sub":"",
      "name": "Sherin V Thomas",
      "ph": "7558003638"
    },
    {
      "id": "3",
      "title": "Finance Coordinator",
      "sub":"",
      "name": "Gladson T Lalu",
      "ph": "8086284556"
    },
    {
      "id": "4",
      "title": "Sponsorship Coordinator",
      "sub":"",
      "name": "Adithyanath S S",
      "ph": "9847565991"
    },
    {
      "id": "5",
      "title": "Cultural Event Manager",
      "sub":"",
      "name": "B S Adithya",
      "ph": "7510556352"
    },
    {
      "id": "6",
      "title": "Technical Event Manager",
      "sub":"",
      "name": "Albin Mathew Joseph",
      "ph": "9961019157"
    },
    {
      "id": "7",
      "title": "Exhibition Coordinator",
      "sub": "Civil Engineering",
      "name": "Kasinath. P",
      "ph": "6238216614"
    },
    {
      "id": "8",
      "title": "Exhibition Coordinator",
      "sub": "Computer Science",
      "name": "Jeena Joy",
      "ph": "8848046611"
    },
    {
      "id": "9",
      "title": "Exhibition Coordinator",
      "sub": "Electronics & Communication",
      "name": "Sneha S Nair",
      "ph": "9645318060"
    },
    {
      "id": "10",
      "title": "Exhibition Coordinator",
      "sub": "Electrical & Electronics",
      "name": "Aswin A S",
      "ph": "9847151730"
    },
    {
      "id": "11",
      "title": "Public Relations & Enquiry",
      "sub":"",
      "name": "Kavya Mariya Simon",
      "ph": "7306193692"
    }
  ]
}
